Workbook

Sheet Market size
B2: MARKET SIZE AVAILABLE
B5: WHY Setting targets precedes strategy formulation. Market size and profitability are the only viable context within which the business can set targets and develop strategies. WHAT Determine the size of the market in terms of total size and total profit pool. HOW 1. Define the number of customers who are potential buyers for your product and service. 2. Determine how many products or services they buy per year. 3. Determine the average price they pay per product/ service. 4. The multiplication of the above 3 variables will give you the size of the market. 5. Multiply by your average gross margin %. 6. This will provide you with the overall profit pool in the market. | E5: Total Number of Customers | J5: 10000
E6: Average Spending per Customer | J6: 35000
E7: Average Number of Purchases per Year | J7: 1
E8: Gross Profit Margin (%) | J8: 0.15
E11: Market Size | F11: =YEAR(TODAY()) -> 2025 | H11: =J5*J6*J7 -> 350000000
E13: Profit Pool | F13: =YEAR(TODAY()) -> 2025 | H13: =H11*J8 -> 52500000
G15: Next | H15: Driving Forces Brainstorm

Sheet Market Attractiveness
B1: Optional tool in case you seek geographical expansion
B2: MARKET ATTRACTIVENESS INDEX
B4: Averaged numbers from base country | H4: Country 1 | I4: Country 2 | J4: Country 3 | K4: Country 4 | L4: Country 5 | M4: Country 6 | N4: Country 7 | O4: Country 8 | P4: Country 9 | Q4: Country 10 | T4: The model provides a combination of the market reality and your own assessment of the strategic relevance of the country. It is a good starting point to evaluate alternative directions for expansion
B6: Sales per person - USD | E6: 5 | G6: population "000
B7: profit per person USD | E7: 1
G8: market size adjustment | T8: 1 | U8: Do calculations for one BASE country - sales per person and profit per person - E6 and E7
B9: Size and profitability adjustment | G9: Market size '000 | H9: =H6*H8*$E$6 -> 0 | I9: =I6*I8*$E$6 -> 0 | J9: =J6*J8*$E$6 -> 0 | K9: =K6*K8*$E$6 -> 0 | L9: =L6*L8*$E$6 -> 0 | M9: =M6*M8*$E$6 -> 0 | N9: =N6*N8*$E$6 -> 0 | O9: =O6*O8*$E$6 -> 0 | ... Q9: =Q6*Q8*$E$6 -> 0 | R9: =AVERAGE(H9:Q9) -> 0 | T9: 2 | U9: Choose the counties for which you want to perform the analyses and input population in row 6
G10: average adjustment | H10: =(H9*100%)/$R$9 -> #DIV/0! | I10: =(I9*100%)/$R$9 -> #DIV/0! | J10: =(J9*100%)/$R$9 -> #DIV/0! | K10: =(K9*100%)/$R$9 -> #DIV/0! | L10: =(L9*100%)/$R$9 -> #DIV/0! | M10: =(M9*100%)/$R$9 -> #DIV/0! | N10: =(N9*100%)/$R$9 -> #DIV/0! | O10: =(O9*100%)/$R$9 -> #DIV/0! | ... Q10: =(Q9*100%)/$R$9 -> #DIV/0!
B11: Much better compared to base | E11: 1.5 | G11: market size index (-3 to +3) | H11: =IFERROR(IF(H10<$E$16,"-3",IF(H10<$E$14,"-2",IF(AND(H10>=$E$14,H10<=$E$13),"-1",IF(H10=$E$13,0,IF(AND(H10>$E$13,H10<$E$12),1,IF(AND(H10>$E$12,H10<$E$11),2,IF(H10>$E$11,"3"))))))),"") | I11: =IFERROR(IF(I10<$E$16,"-3",IF(I10<$E$14,"-2",IF(AND(I10>=$E$14,I10<=$E$13),"-1",IF(I10=$E$13,0,IF(AND(I10>$E$13,I10<$E$12),1,IF(AND(I10>$E$12,I10<$E$11),2,IF(I10>$E$11,"3"))))))),"") | J11: =IFERROR(IF(J10<$E$16,"-3",IF(J10<$E$14,"-2",IF(AND(J10>=$E$14,J10<=$E$13),"-1",IF(J10=$E$13,0,IF(AND(J10>$E$13,J10<$E$12),1,IF(AND(J10>$E$12,J10<$E$11),2,IF(J10>$E$11,"3"))))))),"") | K11: =IFERROR(IF(K10<$E$16,"-3",IF(K10<$E$14,"-2",IF(AND(K10>=$E$14,K10<=$E$13),"-1",IF(K10=$E$13,0,IF(AND(K10>$E$13,K10<$E$12),1,IF(AND(K10>$E$12,K10<$E$11),2,IF(K10>$E$11,"3"))))))),"") | L11: =IFERROR(IF(L10<$E$16,"-3",IF(L10<$E$14,"-2",IF(AND(L10>=$E$14,L10<=$E$13),"-1",IF(L10=$E$13,0,IF(AND(L10>$E$13,L10<$E$12),1,IF(AND(L10>$E$12,L10<$E$11),2,IF(L10>$E$11,"3"))))))),"") | M11: =IFERROR(IF(M10<$E$16,"-3",IF(M10<$E$14,"-2",IF(AND(M10>=$E$14,M10<=$E$13),"-1",IF(M10=$E$13,0,IF(AND(M10>$E$13,M10<$E$12),1,IF(AND(M10>$E$12,M10<$E$11),2,IF(M10>$E$11,"3"))))))),"") | N11: =IFERROR(IF(N10<$E$16,"-3",IF(N10<$E$14,"-2",IF(AND(N10>=$E$14,N10<=$E$13),"-1",IF(N10=$E$13,0,IF(AND(N10>$E$13,N10<$E$12),1,IF(AND(N10>$E$12,N10<$E$11),2,IF(N10>$E$11,"3"))))))),"") | O11: =IFERROR(IF(O10<$E$16,"-3",IF(O10<$E$14,"-2",IF(AND(O10>=$E$14,O10<=$E$13),"-1",IF(O10=$E$13,0,IF(AND(O10>$E$13,O10<$E$12),1,IF(AND(O10>$E$12,O10<$E$11),2,IF(O10>$E$11,"3"))))))),"") | ... Q11: =IFERROR(IF(Q10<$E$16,"-3",IF(Q10<$E$14,"-2",IF(AND(Q10>=$E$14,Q10<=$E$13),"-1",IF(Q10=$E$13,0,IF(AND(Q10>$E$13,Q10<$E$12),1,IF(AND(Q10>$E$12,Q10<$E$11),2,IF(Q10>$E$11,"3"))))))),"") | T11: 3 | U11: Adjust the market size per country in row 8 in accordance with the scoring mechanism
B12: better than base | E12: 1.25 | T12: 4 | U12: Adjust the profit pool per country in row 13 per country according to the scoring adjustment
B13: same | E13: 1 | G13: Profit pool adjustment | H13: 1 | I13: 1 | J13: 1 | K13: 1 | L13: 1 | M13: 0 | N13: 0 | O13: 0 | P13: 0 | Q13: 0 | T13: 5 | U13: Determine the country attractiveness index (-3 - +3) in row 18
B14: worse than base | E14: 0.75 | G14: Profit pool '000 | H14: =$E$7*H6*H13 -> 0 | I14: =$E$7*I6*I13 -> 0 | J14: =$E$7*J6*J13 -> 0 | K14: =$E$7*K6*K13 -> 0 | L14: =$E$7*L6*L13 -> 0 | M14: =$E$7*M6*M13 -> 0 | N14: =$E$7*N6*N13 -> 0 | O14: =$E$7*O6*O13 -> 0 | ... Q14: =$E$7*Q6*Q13 -> 0 | R14: =AVERAGE(H14:Q14) -> 0
G15: average adjustment | H15: =(H14*100%)/$R$14 -> #DIV/0! | I15: =(I14*100%)/$R$14 -> #DIV/0! | J15: =(J14*100%)/$R$14 -> #DIV/0! | K15: =(K14*100%)/$R$14 -> #DIV/0! | L15: =(L14*100%)/$R$14 -> #DIV/0! | M15: =(M14*100%)/$R$14 -> #DIV/0! | N15: =(N14*100%)/$R$14 -> #DIV/0! | O15: =(O14*100%)/$R$14 -> #DIV/0! | ... Q15: =(Q14*100%)/$R$14 -> #DIV/0! | U15: row 19 automatically calculates the country attractiveness index
B16: much worse than base | E16: 0.5 | G16: profit size index (-3 to +3) | H16: =IFERROR(IF(H15<$E$16,"-3",IF(H15<$E$14,"-2",IF(AND(H15>=$E$14,H15<=$E$13),"-1",IF(H15=$E$13,0,IF(AND(H15>$E$13,H15<$E$12),1,IF(AND(H15>$E$12,H15<$E$11),2,IF(H15>$E$11,"3"))))))),"") | I16: =IFERROR(IF(I15<$E$16,"-3",IF(I15<$E$14,"-2",IF(AND(I15>=$E$14,I15<=$E$13),"-1",IF(I15=$E$13,0,IF(AND(I15>$E$13,I15<$E$12),1,IF(AND(I15>$E$12,I15<$E$11),2,IF(I15>$E$11,"3"))))))),"") | J16: =IFERROR(IF(J15<$E$16,"-3",IF(J15<$E$14,"-2",IF(AND(J15>=$E$14,J15<=$E$13),"-1",IF(J15=$E$13,0,IF(AND(J15>$E$13,J15<$E$12),1,IF(AND(J15>$E$12,J15<$E$11),2,IF(J15>$E$11,"3"))))))),"") | K16: =IFERROR(IF(K15<$E$16,"-3",IF(K15<$E$14,"-2",IF(AND(K15>=$E$14,K15<=$E$13),"-1",IF(K15=$E$13,0,IF(AND(K15>$E$13,K15<$E$12),1,IF(AND(K15>$E$12,K15<$E$11),2,IF(K15>$E$11,"3"))))))),"") | L16: =IFERROR(IF(L15<$E$16,"-3",IF(L15<$E$14,"-2",IF(AND(L15>=$E$14,L15<=$E$13),"-1",IF(L15=$E$13,0,IF(AND(L15>$E$13,L15<$E$12),1,IF(AND(L15>$E$12,L15<$E$11),2,IF(L15>$E$11,"3"))))))),"") | M16: =IFERROR(IF(M15<$E$16,"-3",IF(M15<$E$14,"-2",IF(AND(M15>=$E$14,M15<=$E$13),"-1",IF(M15=$E$13,0,IF(AND(M15>$E$13,M15<$E$12),1,IF(AND(M15>$E$12,M15<$E$11),2,IF(M15>$E$11,"3"))))))),"") | N16: =IFERROR(IF(N15<$E$16,"-3",IF(N15<$E$14,"-2",IF(AND(N15>=$E$14,N15<=$E$13),"-1",IF(N15=$E$13,0,IF(AND(N15>$E$13,N15<$E$12),1,IF(AND(N15>$E$12,N15<$E$11),2,IF(N15>$E$11,"3"))))))),"") | O16: =IFERROR(IF(O15<$E$16,"-3",IF(O15<$E$14,"-2",IF(AND(O15>=$E$14,O15<=$E$13),"-1",IF(O15=$E$13,0,IF(AND(O15>$E$13,O15<$E$12),1,IF(AND(O15>$E$12,O15<$E$11),2,IF(O15>$E$11,"3"))))))),"") | ... Q16: =IFERROR(IF(Q15<$E$16,"-3",IF(Q15<$E$14,"-2",IF(AND(Q15>=$E$14,Q15<=$E$13),"-1",IF(Q15=$E$13,0,IF(AND(Q15>$E$13,Q15<$E$12),1,IF(AND(Q15>$E$12,Q15<$E$11),2,IF(Q15>$E$11,"3"))))))),"") | U16: Final score is automatically calculated in row 20
B18: Country attractiveness adjustment | G18: country attractiveness | U18: Please only work on the BLUE cells
B19: very attractive | E19: 3
B20: attractive | E20: 2 | G20: Overall attractiveness index | H20: =IFERROR(H11+H16+H18,"") | I20: =IFERROR(I11+I16+I18,"") | J20: =IFERROR(J11+J16+J18,"") | K20: =IFERROR(K11+K16+K18,"") | L20: =IFERROR(L11+L16+L18,"") | M20: =IFERROR(M11+M16+M18,"") | N20: =IFERROR(N11+N16+N18,"") | O20: =IFERROR(O11+O16+O18,"") | ... Q20: =IFERROR(Q11+Q16+Q18,"")
B21: neutral | E21: 1
B22: not attractive | E22: -2
B23: very unattractive | E23: -3

Sheet Driving Forces brainstorm
E2: DRIVING FORCES BRAINSTORM | M2: TOP DIRIVING FORCES
C4: Rank | E4: WHY So the ability to predict the future is the ability to understand the driving forces. This tool will help you determine what are the forces in the environment that are going to have an impact on these numbers over the next three, four years. WHAT Identify and describe the main driving forces today that will determine the changes in your industry in the next 3 years. HOW 1. Create a list of the driving forces that are visible today. 2. Evaluate their potential impact on the industry • 1 - very low impact • 5 - very high impact 3. Evaluate the probability of occurence • 1 - very low probability • 5 - very high probability MISTAKES TO AVOID 1. Not having the top 3-5 driving forces with biggest impact. 2. Not understanding their impact on the industry. 3. Not eliminating the blind spots that hide some driving forces. 4. Not underestimate the speed and impact of technology. 5. Not interpret correctly the impact on consumer’s behaviour. | G4: List Driving Forces | H4: Impact (1-5) | I4: Probability (1-5) | J4: Score | M4: Top 10 Driving Forces
A6: =IF(G6<>"",COUNTIF($J6:J$6,J6),"") | B6: =IF(G6<>"",IFERROR(RANK(J6,$J$6:$J$24,0),1),"") | C6: =IF(ISNUMBER(B6),B6+A6-1,"") | J6: =IF(G6<>"",(2*H6+I6),"") | L6: 1 | M6: =IFERROR(INDEX($A$4:$I$1048576,MATCH($L6,$C$4:$C$24,0),MATCH($G$4,$4:$4,0)),"")
A7: =IF(G7<>"",COUNTIF($J$6:J7,J7),"") | B7: =IF(G7<>"",IFERROR(RANK(J7,$J$6:$J$24,0),1),"") | C7: =IF(ISNUMBER(B7),B7+A7-1,"") | J7: =IF(G7<>"",(2*H7+I7),"")
A8: =IF(G8<>"",COUNTIF($J$6:J8,J8),"") | B8: =IF(G8<>"",IFERROR(RANK(J8,$J$6:$J$24,0),1),"") | C8: =IF(ISNUMBER(B8),B8+A8-1,"") | J8: =IF(G8<>"",(2*H8+I8),"")
A9: =IF(G9<>"",COUNTIF($J$6:J9,J9),"") | B9: =IF(G9<>"",IFERROR(RANK(J9,$J$6:$J$24,0),1),"") | C9: =IF(ISNUMBER(B9),B9+A9-1,"") | J9: =IF(G9<>"",(2*H9+I9),"") | L9: 2 | M9: =IFERROR(INDEX($A$4:$I$1048576,MATCH($L9,$C$4:$C$24,0),MATCH($G$4,$4:$4,0)),"")
A10: =IF(G10<>"",COUNTIF($J$6:J10,J10),"") | B10: =IF(G10<>"",IFERROR(RANK(J10,$J$6:$J$24,0),1),"") | C10: =IF(ISNUMBER(B10),B10+A10-1,"") | J10: =IF(G10<>"",(2*H10+I10),"") | L10: 3 | M10: =IFERROR(INDEX($A$4:$I$1048576,MATCH($L10,$C$4:$C$24,0),MATCH($G$4,$4:$4,0)),"")
A11: =IF(G11<>"",COUNTIF($J$6:J11,J11),"") | B11: =IF(G11<>"",IFERROR(RANK(J11,$J$6:$J$24,0),1),"") | C11: =IF(ISNUMBER(B11),B11+A11-1,"") | J11: =IF(G11<>"",(2*H11+I11),"") | L11: 4 | M11: =IFERROR(INDEX($A$4:$I$1048576,MATCH($L11,$C$4:$C$24,0),MATCH($G$4,$4:$4,0)),"")
A12: =IF(G12<>"",COUNTIF($J$6:J12,J12),"") | B12: =IF(G12<>"",IFERROR(RANK(J12,$J$6:$J$24,0),1),"") | C12: =IF(ISNUMBER(B12),B12+A12-1,"") | J12: =IF(G12<>"",(2*H12+I12),"") | L12: 5 | M12: =IFERROR(INDEX($A$4:$I$1048576,MATCH($L12,$C$4:$C$24,0),MATCH($G$4,$4:$4,0)),"")
A13: =IF(G13<>"",COUNTIF($J$6:J13,J13),"") | B13: =IF(G13<>"",IFERROR(RANK(J13,$J$6:$J$24,0),1),"") | C13: =IF(ISNUMBER(B13),B13+A13-1,"") | J13: =IF(G13<>"",(2*H13+I13),"") | L13: 6 | M13: =IFERROR(INDEX($A$4:$I$1048576,MATCH($L13,$C$4:$C$24,0),MATCH($G$4,$4:$4,0)),"")
A14: =IF(G14<>"",COUNTIF($J$6:J14,J14),"") | B14: =IF(G14<>"",IFERROR(RANK(J14,$J$6:$J$24,0),1),"") | C14: =IF(ISNUMBER(B14),B14+A14-1,"") | J14: =IF(G14<>"",(2*H14+I14),"") | L14: 7 | M14: =IFERROR(INDEX($A$4:$I$1048576,MATCH($L14,$C$4:$C$24,0),MATCH($G$4,$4:$4,0)),"")
A15: =IF(G15<>"",COUNTIF($J$6:J15,J15),"") | B15: =IF(G15<>"",IFERROR(RANK(J15,$J$6:$J$24,0),1),"") | C15: =IF(ISNUMBER(B15),B15+A15-1,"") | J15: =IF(G15<>"",(2*H15+I15),"")
A16: =IF(G16<>"",COUNTIF($J$6:J16,J16),"") | B16: =IF(G16<>"",IFERROR(RANK(J16,$J$6:$J$24,0),1),"") | C16: =IF(ISNUMBER(B16),B16+A16-1,"") | J16: =IF(G16<>"",(2*H16+I16),"")
A17: =IF(G17<>"",COUNTIF($J$6:J17,J17),"") | B17: =IF(G17<>"",IFERROR(RANK(J17,$J$6:$J$24,0),1),"") | C17: =IF(ISNUMBER(B17),B17+A17-1,"") | J17: =IF(G17<>"",(2*H17+I17),"")
A18: =IF(G18<>"",COUNTIF($J$6:J18,J18),"") | B18: =IF(G18<>"",IFERROR(RANK(J18,$J$6:$J$24,0),1),"") | C18: =IF(ISNUMBER(B18),B18+A18-1,"") | J18: =IF(G18<>"",(2*H18+I18),"")
A19: =IF(G19<>"",COUNTIF($J$6:J19,J19),"") | B19: =IF(G19<>"",IFERROR(RANK(J19,$J$6:$J$24,0),1),"") | C19: =IF(ISNUMBER(B19),B19+A19-1,"") | J19: =IF(G19<>"",(2*H19+I19),"")
A20: =IF(G20<>"",COUNTIF($J$6:J20,J20),"") | B20: =IF(G20<>"",IFERROR(RANK(J20,$J$6:$J$24,0),1),"") | C20: =IF(ISNUMBER(B20),B20+A20-1,"") | J20: =IF(G20<>"",(2*H20+I20),"")
A21: =IF(G21<>"",COUNTIF($J$6:J21,J21),"") | B21: =IF(G21<>"",IFERROR(RANK(J21,$J$6:$J$24,0),1),"") | C21: =IF(ISNUMBER(B21),B21+A21-1,"") | J21: =IF(G21<>"",(2*H21+I21),"")
A22: =IF(G22<>"",COUNTIF($J$6:J22,J22),"") | B22: =IF(G22<>"",IFERROR(RANK(J22,$J$6:$J$24,0),1),"") | C22: =IF(ISNUMBER(B22),B22+A22-1,"") | J22: =IF(G22<>"",(2*H22+I22),"") | M22: Back | N22: Market Size
A23: =IF(G23<>"",COUNTIF($J$6:J23,J23),"") | B23: =IF(G23<>"",IFERROR(RANK(J23,$J$6:$J$24,0),1),"") | C23: =IF(ISNUMBER(B23),B23+A23-1,"") | J23: =IF(G23<>"",(2*H23+I23),"")
A24: =IF(G24<>"",COUNTIF($J$6:J24,J24),"") | B24: =IF(G24<>"",IFERROR(RANK(J24,$J$6:$J$24,0),1),"") | C24: =IF(ISNUMBER(B24),B24+A24-1,"") | J24: =IF(G24<>"",(2*H24+I24),"") | M24: Next | N24: Driving Forces Impact

Sheet Driving Forces impact
B2: DRIVING FORCES IMPACT
B4: WHY We are creating a strategy not for today, but for the next 3 years WHAT Understand how the market will change in the next years by estimating the effect of the driving forces on: 1. Number of clients 2. Their spending 3. Their number of purchases 4. Your gross profit margin HOW Understand what could be the impact of driving forces on: 1. Insert by what % amount (positive or negative) each driving force will change the four pillars (e.g. average spending will increase by 10%) | I4: ='Driving Forces brainstorm'!M6 | J4: ='Driving Forces brainstorm'!M9 | K4: ='Driving Forces brainstorm'!M10 | L4: ='Driving Forces brainstorm'!M11 | M4: ='Driving Forces brainstorm'!M12 | N4: ='Driving Forces brainstorm'!M13 | O4: ='Driving Forces brainstorm'!M14
D5: Total Number of Customers | I5: 0.05 | J5: 0.1 | K5: -0.05 | P5: =(1+SUM(I5:O5))*'Market size'!J5 -> 11000
D6: Average Spending per Customer | P6: =(1+SUM(I6:O6))*'Market size'!J6 -> 35000
D7: Average Number of Purchases per Year | P7: =(1+SUM(I7:O7))*'Market size'!J7 -> 1
D8: Gross Profit Margin (%) | I8: 1 | P8: =(1+SUM(I8:O8))*'Market size'!J8 -> 0.3
D10: Customers | E10: =YEAR(TODAY())+3 -> 2028 | G10: =P5 -> 11000
D12: Market Size | E12: =YEAR(TODAY())+3 -> 2028 | G12: ='Market size'!H11*((1+SUM(I5:O5))*(1+SUM(I6:O6))*(1+SUM(I7:O7))) -> 3.85e+08 | M12: Back | N12: Driving Forces Brainstorm | P12: =P5*P6*P7 -> 385000000
D14: Profit Pool | E14: =YEAR(TODAY())+3 -> 2028 | G14: =G12*'Market size'!J8*(1+SUM(I8:O8)) -> 1.155e+08 | M14: Next | N14: Segment Brainstorm | P14: =P12*P8 -> 115500000
